odoo/addons/fieldservice_timesheet/README.rst
odoo/addons/fieldservice_timesheet/__init__.py
odoo/addons/fieldservice_timesheet/__manifest__.py
odoo/addons/fieldservice_timesheet/i18n/fieldservice_timesheet.pot
odoo/addons/fieldservice_timesheet/i18n/it.po
odoo/addons/fieldservice_timesheet/models/__init__.py
odoo/addons/fieldservice_timesheet/models/fsm_order.py
odoo/addons/fieldservice_timesheet/models/hr_timesheet.py
odoo/addons/fieldservice_timesheet/readme/CONTRIBUTORS.md
odoo/addons/fieldservice_timesheet/readme/DESCRIPTION.md
odoo/addons/fieldservice_timesheet/report/__init__.py
odoo/addons/fieldservice_timesheet/report/report_timesheet_templates.xml
odoo/addons/fieldservice_timesheet/report/timesheets_analysis_report.py
odoo/addons/fieldservice_timesheet/static/description/icon.png
odoo/addons/fieldservice_timesheet/static/description/index.html
odoo/addons/fieldservice_timesheet/views/fsm_order.xml
odoo/addons/fieldservice_timesheet/views/hr_timesheet.xml
odoo_addon_fieldservice_timesheet-18.0.1.0.0.4.dist-info/METADATA
odoo_addon_fieldservice_timesheet-18.0.1.0.0.4.dist-info/WHEEL
odoo_addon_fieldservice_timesheet-18.0.1.0.0.4.dist-info/top_level.txt
odoo_addon_fieldservice_timesheet-18.0.1.0.0.4.dist-info/RECORD
